compensateflowcyte.py
exportflowcyte.py
gateflowcyte.py
importflowcyte.py
napari_jflowcyte-0.0.9.dist-info/METADATA
napari_jflowcyte-0.0.9.dist-info/WHEEL
napari_jflowcyte-0.0.9.dist-info/top_level.txt
napari_jflowcyte-0.0.9.dist-info/RECORD
